requela/__init__.py
requela/dataclasses.py
requela/exceptions.py
requela/grammar.lark
requela/parser.py
requela/rules.py
requela/transformer.py
requela/builders/__init__.py
requela/builders/base.py
requela/builders/django.py
requela/builders/sqlalchemy.py
requela-0.1.18.dist-info/METADATA
requela-0.1.18.dist-info/WHEEL
requela-0.1.18.dist-info/licenses/LICENSE.txt
requela-0.1.18.dist-info/RECORD
