Metadata-Version: 2.4
Name: requela
Version: 0.1.18
Summary: Resource Query Language to ORM
Project-URL: Homepage, https://github.com/softwareone-platform/requela
Project-URL: Documentation, https://github.com/softwareone-platform/requela#readme
Project-URL: Repository, https://github.com/softwareone-platform/requela.git
Author: SoftwareOne AG
License:                                  Apache License
License-File: LICENSE.txt
Keywords: filter,orm,query,rql,sqlalchemy
Classifier: Development Status :: 4 - Beta
Classifier: Intended Audience :: Developers
Classifier: License :: OSI Approved :: Apache Software License
Classifier: Programming Language :: Python :: 3
Classifier: Programming Language :: Python :: 3.12
Classifier: Topic :: Database :: Front-Ends
Classifier: Topic :: Software Development :: Libraries :: Python Modules
Requires-Python: <4,>=3.12
Requires-Dist: lark>=1.2.2
Requires-Dist: pytest-randomly>=3.16.0
